brminer/__init__.py
brminer-0.0.3.dist-info/LICENSE
brminer-0.0.3.dist-info/METADATA
brminer-0.0.3.dist-info/WHEEL
brminer-0.0.3.dist-info/top_level.txt
brminer-0.0.3.dist-info/RECORD
