Metadata-Version: 2.1
Name: brminer
Version: 0.0.3
Summary: BaggingRandomMiner is an ensemble of weak one-class classifiers based on dissimilarities. In the training phase, every weak classifier is built using Bagging and computing a threshold of dissimilarities. In the classification phase, the classification scores of the weak classifiers are averaged, and every weak classifier computes its score based on the dissimilarity to the nearest neighbor and the threshold computed in the training phase.
Home-page: https://github.com/octavioloyola/BRM
Author: Juan Carlos Velazco Rossell, Miguel Angel Medina Pérez and Octavio Loyola Gonzáles
Author-email: miguelmedinaperez@gmail.com
License: MIT
Platform: UNKNOWN
Classifier: Programming Language :: Python :: 3
Classifier: Operating System :: OS Independent
Requires-Python: >=2.7
Requires-Dist: scikit-learn
Requires-Dist: pandas
Requires-Dist: numpy
